hoa/__init__.py
hoa/__version__.py
hoa/ast/__init__.py
hoa/ast/acceptance.py
hoa/ast/boolean_expression.py
hoa/ast/label.py
hoa/core.py
hoa/dumpers.py
hoa/grammars/hoa.lark
hoa/helpers/__init__.py
hoa/helpers/base.py
hoa/parsers.py
hoa/printers.py
hoa/tools/__init__.py
hoa/tools/pyhoafparser.py
hoa/types.py
hoa_utils-0.1.0.dist-info/entry_points.txt
hoa_utils-0.1.0.dist-info/LICENSE
hoa_utils-0.1.0.dist-info/WHEEL
hoa_utils-0.1.0.dist-info/METADATA
hoa_utils-0.1.0.dist-info/RECORD
