Metadata-Version: 2.1
Name: hoa-utils
Version: 0.1.0
Summary: Utilities for the HOA format.
Home-page: https://whitemech.github.io/hoa-utils
License: LGPL-3.0-or-later
Keywords: HOA,automata,HOA-format
Author: Marco Favorito
Author-email: marco.favorito@gmail.com
Requires-Python: >=3.7,<4.0
Classifier: Development Status :: 2 - Pre-Alpha
Classifier: Intended Audience :: Developers
Classifier: License :: OSI Approved :: GNU Lesser General Public License v3 or later (LGPLv3+)
Classifier: Natural Language :: English
Classifier: Programming Language :: Python :: 3
Classifier: Programming Language :: Python :: 3.7
Classifier: Programming Language :: Python :: 3.8
Requires-Dist: click (>=7.1.2,<8.0.0)
Requires-Dist: lark-parser (>=0.9.0,<0.10.0)
Project-URL: Bug Tracker, https://github.com/whitemech/hoa-utils/issues
Project-URL: Documentation, https://whitemech.github.io/hoa-utils
Project-URL: Pull Requests, https://github.com/whitemech/hoa-utils/pulls
Project-URL: Repository, https://github.com/whitemech/hoa-utils.git
